[
  {
    "id": "lit_philosophy",
    "faculty": "文学部",
    "department": "哲学科",
    "summary": "哲学は驚きから始まる。ものごとの根本を問い、考え抜く力を磨く。",
    "official_url": "https://www.toyo.ac.jp/nyushi/undergraduate/lit/dphi/",
    "source_basis": "official_department_page",
    "tags": [
      "哲学",
      "思想",
      "倫理",
      "問い",
      "人間",
      "論理",
      "宗教",
      "価値観",
      "人文",
      "言語文化",
      "対話",
      "言語",
      "歴史",
      "英語",
      "コミュニケーション",
      "古典",
      "授業",
      "教育",
      "トレーニング",
      "異文化理解",
      "語学学",
      "翻訳",
      "また哲学",
      "ジャンケレヴィッチ音楽論"
    ],
    "areas": [
      "人文",
      "思想",
      "言語文化"
    ],
    "policy_keywords": [
      "哲学",
      "思想",
      "倫理",
      "問い",
      "人文",
      "思想",
      "言語文化"
    ],
    "research_keywords": [
      "哲学",
      "思想",
      "倫理",
      "問い",
      "人間",
      "論理",
      "宗教",
      "価値観",
      "人文",
      "言語文化",
      "対話",
      "言語",
      "歴史",
      "英語",
      "コミュニケーション",
      "古典",
      "授業",
      "教育",
      "トレーニング",
      "異文化理解",
      "語学学",
      "翻訳",
      "また哲学",
      "ジャンケレヴィッチ音楽論",
      "卒業論",
      "宗教・歴史哲学",
      "広大な哲学",
      "死生学",
      "自然環境哲学",
      "芸術哲学",
      "読解・対話・討論",
      "身体表現哲学"
    ],
    "needs_review": true,
    "review_note": "公式の学科ページ・研究室紹介ページ・Web体験授業欄から抽出した研究語彙を追加したドラフトです。正式運用前に各学科で確認してください。"
  },
  {
    "id": "lit_oriental",
    "faculty": "文学部",
    "department": "東洋思想文化学科",
    "summary": "東洋を学び、世界の中に自分が見える視点を育てる。",
    "official_url": "https://www.toyo.ac.jp/nyushi/undergraduate/lit/depc/",
    "source_basis": "official_department_page",
    "tags": [
      "東洋思想",
      "文化",
      "歴史",
      "宗教",
      "アジア",
      "言語",
      "思想",
      "人文",
      "国際文化",
      "化学",
      "地域",
      "仏教",
      "グローバル",
      "授業",
      "教育",
      "東洋思想文化学",
      "古典",
      "国際社会",
      "日本文化",
      "価値観",
      "交通",
      "哲学",
      "教職",
      "英語"
    ],
    "areas": [
      "人文",
      "思想",
      "国際文化"
    ],
    "policy_keywords": [
      "東洋思想",
      "文化",
      "歴史",
      "宗教",
      "人文",
      "思想",
      "国際文化"
    ],
    "research_keywords": [
      "東洋思想",
      "文化",
      "歴史",
      "宗教",
      "アジア",
      "言語",
      "思想",
      "人文",
      "国際文化",
      "化学",
      "地域",
      "仏教",
      "グローバル",
      "授業",
      "教育",
      "東洋思想文化学",
      "古典",
      "国際社会",
      "日本文化",
      "価値観",
      "交通",
      "哲学",
      "教職",
      "英語",
      "都市",
      "また学",
      "中国語・中国哲学文学",
      "事前学",
      "卒業論",
      "東洋学",
      "理惑論",
      "積極的な学"
    ],
    "needs_review": true,
    "review_note": "公式の学科ページ・研究室紹介ページ・Web体験授業欄から抽出した研究語彙を追加したドラフトです。正式運用前に各学科で確認してください。"
  },
  {
    "id": "lit_japanese",
    "faculty": "文学部",
    "department": "日本文学文化学科",
    "summary": "日本を深く知り、世界を見渡す眼を磨く。",
    "official_url": "https://www.toyo.ac.jp/nyushi/undergraduate/lit/djlc/",
    "source_basis": "official_department_page",
    "tags": [
      "日本文学",
      "日本文化",
      "言葉",
      "古典",
      "現代文学",
      "表現",
      "編集",
      "人文",
      "言語文化",
      "共同",
      "グローバル",
      "教育",
      "化学",
      "コミュニケーション",
      "卒業論",
      "古典文学",
      "日本文学文化学",
      "日本語学",
      "比較文学",
      "現代学",
      "近現代文学",
      "国際社会",
      "学習支援",
      "企業"
    ],
    "areas": [
      "人文",
      "言語文化",
      "表現"
    ],
    "policy_keywords": [
      "日本文学",
      "日本文化",
      "言葉",
      "古典",
      "人文",
      "言語文化",
      "表現"
    ],
    "research_keywords": [
      "日本文学",
      "日本文化",
      "言葉",
      "古典",
      "現代文学",
      "表現",
      "編集",
      "人文",
      "言語文化",
      "共同",
      "グローバル",
      "教育",
      "化学",
      "コミュニケーション",
      "卒業論",
      "古典文学",
      "日本文学文化学",
      "日本語学",
      "比較文学",
      "現代学",
      "近現代文学",
      "国際社会",
      "学習支援",
      "企業",
      "共生",
      "地域",
      "思想",
      "政策",
      "言語",
      "グループ学",
      "ジャーナリスト・キャスター・SBI大学",
      "トップリーダー連携教育支援",
      "ヴェネツィア・カフォスカリ大学",
      "地政学",
      "実践女子大学国文学",
      "産官学"
    ],
    "needs_review": true,
    "review_note": "公式の学科ページ・研究室紹介ページ・Web体験授業欄から抽出した研究語彙を追加したドラフトです。正式運用前に各学科で確認してください。"
  },
  {
    "id": "lit_english",
    "faculty": "文学部",
    "department": "英米文学科",
    "summary": "英語の4技能を磨き、英語を通して異文化を理解する。",
    "official_url": "https://www.toyo.ac.jp/nyushi/undergraduate/lit/deal/",
    "source_basis": "official_department_page",
    "tags": [
      "英語",
      "英米文学",
      "異文化理解",
      "翻訳",
      "言語",
      "コミュニケーション",
      "国際文化",
      "表現",
      "語学",
      "授業",
      "米文学",
      "教育",
      "卒業論",
      "英語学",
      "価値観",
      "英文学",
      "英語教育",
      "グローバル",
      "ジェンダー",
      "基礎的な語学",
      "文学的・語学",
      "ICT",
      "化学",
      "思想"
    ],
    "areas": [
      "語学",
      "国際文化",
      "表現"
    ],
    "policy_keywords": [
      "英語",
      "英米文学",
      "異文化理解",
      "翻訳",
      "語学",
      "国際文化",
      "表現"
    ],
    "research_keywords": [
      "英語",
      "英米文学",
      "異文化理解",
      "翻訳",
      "言語",
      "コミュニケーション",
      "国際文化",
      "表現",
      "語学",
      "授業",
      "米文学",
      "教育",
      "卒業論",
      "英語学",
      "価値観",
      "英文学",
      "英語教育",
      "グローバル",
      "ジェンダー",
      "基礎的な語学",
      "文学的・語学",
      "ICT",
      "化学",
      "思想",
      "歴史",
      "留学",
      "論理",
      "幅広く学",
      "文学か語学",
      "海外留学",
      "英文学・米文学・英語学",
      "英文法",
      "英米文学・文化・語学",
      "英語音声学"
    ],
    "needs_review": true,
    "review_note": "公式の学科ページ・研究室紹介ページ・Web体験授業欄から抽出した研究語彙を追加したドラフトです。正式運用前に各学科で確認してください。"
  },
  {
    "id": "lit_history",
    "faculty": "文学部",
    "department": "史学科",
    "summary": "史料と向き合い、今と未来を築く。",
    "official_url": "https://www.toyo.ac.jp/nyushi/undergraduate/lit/dhis/",
    "source_basis": "official_department_page",
    "tags": [
      "歴史",
      "史料",
      "日本史",
      "東洋史",
      "西洋史",
      "文化財",
      "地域",
      "人文",
      "社会理解",
      "博物館",
      "歴史学",
      "授業",
      "英語",
      "フィールドワーク",
      "思想",
      "教育",
      "グローバル",
      "卒業論",
      "日本史学",
      "東洋史学",
      "西洋史学",
      "古典",
      "経済",
      "より多様な歴史学"
    ],
    "areas": [
      "人文",
      "歴史",
      "社会理解"
    ],
    "policy_keywords": [
      "歴史",
      "史料",
      "日本史",
      "東洋史",
      "人文",
      "歴史",
      "社会理解"
    ],
    "research_keywords": [
      "歴史",
      "史料",
      "日本史",
      "東洋史",
      "西洋史",
      "文化財",
      "地域",
      "人文",
      "社会理解",
      "博物館",
      "歴史学",
      "授業",
      "英語",
      "フィールドワーク",
      "思想",
      "教育",
      "グローバル",
      "卒業論",
      "日本史学",
      "東洋史学",
      "西洋史学",
      "古典",
      "経済",
      "より多様な歴史学",
      "博物館学",
      "古文書学",
      "歴史学研究法"
    ],
    "needs_review": true,
    "review_note": "公式の学科ページ・研究室紹介ページ・Web体験授業欄から抽出した研究語彙を追加したドラフトです。正式運用前に各学科で確認してください。"
  },
  {
    "id": "lit_education_human",
    "faculty": "文学部",
    "department": "教育学科 人間発達専攻",
    "summary": "成長し続ける人と、ともにあるための学び。",
    "official_url": "https://www.toyo.ac.jp/nyushi/undergraduate/lit/dedh/",
    "source_basis": "official_department_page",
    "tags": [
      "教育",
      "人間発達",
      "子ども",
      "学び",
      "心理",
      "学校",
      "生涯学習",
      "福祉",
      "教育学",
      "特別支援",
      "心理学",
      "障害",
      "卒業論",
      "生涯学",
      "スポーツ",
      "社会学",
      "哲学",
      "情報",
      "歴史",
      "ユニバーサルデザイン",
      "グローバル",
      "特別支援学",
      "生涯学習概論",
      "高等学"
    ],
    "areas": [
      "教育",
      "心理",
      "福祉"
    ],
    "policy_keywords": [
      "教育",
      "人間発達",
      "子ども",
      "学び",
      "教育",
      "心理",
      "福祉"
    ],
    "research_keywords": [
      "教育",
      "人間発達",
      "子ども",
      "学び",
      "心理",
      "学校",
      "生涯学習",
      "福祉",
      "教育学",
      "特別支援",
      "心理学",
      "障害",
      "卒業論",
      "生涯学",
      "スポーツ",
      "社会学",
      "哲学",
      "情報",
      "歴史",
      "ユニバーサルデザイン",
      "グローバル",
      "特別支援学",
      "生涯学習概論",
      "高等学",
      "デザイン",
      "価値観",
      "高齢者",
      "企業",
      "授業",
      "教職",
      "経営",
      "防災",
      "1年次春学",
      "家族心理学",
      "授業論",
      "教職論"
    ],
    "needs_review": true,
    "review_note": "公式の学科ページ・研究室紹介ページ・Web体験授業欄から抽出した研究語彙を追加したドラフトです。正式運用前に各学科で確認してください。"
  },
  {
    "id": "lit_education_primary",
    "faculty": "文学部",
    "department": "教育学科 初等教育専攻",
    "summary": "理論と実践をつなぎ、確かな指導力を磨く。",
    "official_url": "https://www.toyo.ac.jp/nyushi/undergraduate/lit/dedp/",
    "source_basis": "official_department_page",
    "tags": [
      "小学校教員",
      "教育",
      "授業",
      "子ども",
      "学校",
      "実践",
      "教職",
      "資格",
      "教育学",
      "グローバル",
      "英語",
      "卒業論",
      "コミュニケーション",
      "情報",
      "特別支援",
      "人間発達",
      "英語教育",
      "地域",
      "心理",
      "留学",
      "開発",
      "1年次春学",
      "また海外留学",
      "心理学"
    ],
    "areas": [
      "教育",
      "資格",
      "子ども"
    ],
    "policy_keywords": [
      "小学校教員",
      "教育",
      "授業",
      "子ども",
      "教育",
      "資格",
      "子ども"
    ],
    "research_keywords": [
      "小学校教員",
      "教育",
      "授業",
      "子ども",
      "学校",
      "実践",
      "教職",
      "資格",
      "教育学",
      "グローバル",
      "英語",
      "卒業論",
      "コミュニケーション",
      "情報",
      "特別支援",
      "人間発達",
      "英語教育",
      "地域",
      "心理",
      "留学",
      "開発",
      "1年次春学",
      "また海外留学",
      "心理学",
      "教育学卒論"
    ],
    "needs_review": true,
    "review_note": "公式の学科ページ・研究室紹介ページ・Web体験授業欄から抽出した研究語彙を追加したドラフトです。正式運用前に各学科で確認してください。"
  },
  {
    "id": "lit_intercultural",
    "faculty": "文学部",
    "department": "国際文化コミュニケーション学科",
    "summary": "自らと他者を結び、文化と言葉を通して世界を考える。",
    "official_url": "https://www.toyo.ac.jp/nyushi/undergraduate/lit/dicc/",
    "source_basis": "official_department_page",
    "tags": [
      "国際文化",
      "コミュニケーション",
      "英語",
      "多文化",
      "翻訳",
      "表現",
      "異文化",
      "語学",
      "言語",
      "留学",
      "教育",
      "授業",
      "歴史",
      "価値観",
      "博物館",
      "学校",
      "インテリア",
      "グローバル",
      "博物館学",
      "国際文化コミュニケーション学",
      "外国人留学",
      "日本文化",
      "ゲーム",
      "AI"
    ],
    "areas": [
      "国際文化",
      "語学",
      "表現"
    ],
    "policy_keywords": [
      "国際文化",
      "コミュニケーション",
      "英語",
      "多文化",
      "国際文化",
      "語学",
      "表現"
    ],
    "research_keywords": [
      "国際文化",
      "コミュニケーション",
      "英語",
      "多文化",
      "翻訳",
      "表現",
      "異文化",
      "語学",
      "言語",
      "留学",
      "教育",
      "授業",
      "歴史",
      "価値観",
      "博物館",
      "学校",
      "インテリア",
      "グローバル",
      "博物館学",
      "国際文化コミュニケーション学",
      "外国人留学",
      "日本文化",
      "ゲーム",
      "AI",
      "共生",
      "哲学",
      "思想",
      "法律",
      "設計",
      "2024年度学科優秀論",
      "卒業論",
      "第二言語学",
      "英語学"
    ],
    "needs_review": true,
    "review_note": "公式の学科ページ・研究室紹介ページ・Web体験授業欄から抽出した研究語彙を追加したドラフトです。正式運用前に各学科で確認してください。"
  },
  {
    "id": "econ_economics",
    "faculty": "経済学部",
    "department": "経済学科",
    "summary": "経済の理論を学び、現実の経済を知る。",
    "official_url": "https://www.toyo.ac.jp/nyushi/undergraduate/eco/deco/",
    "source_basis": "official_department_page",
    "tags": [
      "経済",
      "金融",
      "財政",
      "市場",
      "統計",
      "データ",
      "政策",
      "社会科学",
      "論理",
      "経済学",
      "情報",
      "地域",
      "授業",
      "教育",
      "グローバル",
      "卒業論",
      "子ども",
      "企業",
      "哲学",
      "広告",
      "歴史",
      "空間",
      "設計",
      "都市"
    ],
    "areas": [
      "経済",
      "社会科学",
      "データ"
    ],
    "policy_keywords": [
      "経済",
      "金融",
      "財政",
      "市場",
      "経済",
      "社会科学",
      "データ"
    ],
    "research_keywords": [
      "経済",
      "金融",
      "財政",
      "市場",
      "統計",
      "データ",
      "政策",
      "社会科学",
      "論理",
      "経済学",
      "情報",
      "地域",
      "授業",
      "教育",
      "グローバル",
      "卒業論",
      "子ども",
      "企業",
      "哲学",
      "広告",
      "歴史",
      "空間",
      "設計",
      "都市",
      "1年次春学",
      "広く深く学",
      "書く・話す・議論",
      "経済政策",
      "非対称情報"
    ],
    "needs_review": true,
    "review_note": "公式の学科ページ・研究室紹介ページ・Web体験授業欄から抽出した研究語彙を追加したドラフトです。正式運用前に各学科で確認してください。"
  },
  {
    "id": "econ_international",
    "faculty": "経済学部",
    "department": "国際経済学科",
    "summary": "グローバル経済の課題を捉え、解決へ導く。",
    "official_url": "https://www.toyo.ac.jp/nyushi/undergraduate/eco/diec/",
    "source_basis": "official_department_page",
    "tags": [
      "国際経済",
      "貿易",
      "開発",
      "グローバル",
      "金融",
      "英語",
      "政策",
      "経済",
      "国際",
      "社会課題",
      "地域",
      "経済学",
      "コミュニケーション",
      "言語",
      "国際経済学",
      "企業",
      "教育",
      "イノベーション",
      "ファイナンス",
      "情報",
      "留学",
      "データ分析",
      "卒業論",
      "国際開発"
    ],
    "areas": [
      "経済",
      "国際",
      "社会課題"
    ],
    "policy_keywords": [
      "国際経済",
      "貿易",
      "開発",
      "グローバル",
      "経済",
      "国際",
      "社会課題"
    ],
    "research_keywords": [
      "国際経済",
      "貿易",
      "開発",
      "グローバル",
      "金融",
      "英語",
      "政策",
      "経済",
      "国際",
      "社会課題",
      "地域",
      "経済学",
      "コミュニケーション",
      "言語",
      "国際経済学",
      "企業",
      "教育",
      "イノベーション",
      "ファイナンス",
      "情報",
      "留学",
      "データ分析",
      "卒業論",
      "国際開発",
      "インフラ",
      "システム",
      "国際社会",
      "半導体",
      "AI",
      "学校",
      "森林",
      "構造",
      "歴史",
      "観光",
      "より発展的な学",
      "中国・蘇州大学"
    ],
    "needs_review": true,
    "review_note": "公式の学科ページ・研究室紹介ページ・Web体験授業欄から抽出した研究語彙を追加したドラフトです。正式運用前に各学科で確認してください。"
  },
  {
    "id": "econ_policy",
    "faculty": "経済学部",
    "department": "総合政策学科",
    "summary": "社会の課題に向き合い、協働と共創で社会を導く。",
    "official_url": "https://www.toyo.ac.jp/nyushi/undergraduate/eco/dpol/",
    "source_basis": "official_department_page",
    "tags": [
      "政策",
      "地域",
      "公共",
      "行政",
      "社会課題",
      "データ",
      "まちづくり",
      "社会科学",
      "経済",
      "リーダーシップ",
      "行動",
      "総合政策",
      "データサイエンス",
      "経済学",
      "総合政策学",
      "医療",
      "情報",
      "教育",
      "設計",
      "エネルギー",
      "データ分析",
      "AI",
      "授業",
      "福祉"
    ],
    "areas": [
      "政策",
      "社会科学",
      "地域"
    ],
    "policy_keywords": [
      "政策",
      "地域",
      "公共",
      "行政",
      "政策",
      "社会科学",
      "地域"
    ],
    "research_keywords": [
      "政策",
      "地域",
      "公共",
      "行政",
      "社会課題",
      "データ",
      "まちづくり",
      "社会科学",
      "経済",
      "リーダーシップ",
      "行動",
      "総合政策",
      "データサイエンス",
      "経済学",
      "総合政策学",
      "医療",
      "情報",
      "教育",
      "設計",
      "エネルギー",
      "データ分析",
      "AI",
      "授業",
      "福祉",
      "組織",
      "観光",
      "卒業論",
      "グローバル",
      "公共政策",
      "具体的な政策",
      "異文化理解",
      "メディア",
      "機械学習",
      "社会福祉",
      "SNS",
      "企業"
    ],
    "needs_review": true,
    "review_note": "公式の学科ページ・研究室紹介ページ・Web体験授業欄から抽出した研究語彙を追加したドラフトです。正式運用前に各学科で確認してください。"
  },
  {
    "id": "biz_management",
    "faculty": "経営学部",
    "department": "経営学科",
    "summary": "企業の課題を読み解き、解決策を導く。",
    "official_url": "https://www.toyo.ac.jp/nyushi/undergraduate/fba/dfba/",
    "source_basis": "official_department_page",
    "tags": [
      "経営",
      "企業",
      "組織",
      "起業",
      "戦略",
      "リーダーシップ",
      "ビジネス",
      "実践",
      "社会科学",
      "経営学",
      "情報",
      "英語",
      "グローバル",
      "対話",
      "教育",
      "論理",
      "サステナビリティ",
      "マーケティング",
      "主体的な学",
      "デザイン",
      "社会学",
      "会計",
      "地域",
      "心理"
    ],
    "areas": [
      "ビジネス",
      "社会科学",
      "実践"
    ],
    "policy_keywords": [
      "経営",
      "企業",
      "組織",
      "起業",
      "ビジネス",
      "社会科学",
      "実践"
    ],
    "research_keywords": [
      "経営",
      "企業",
      "組織",
      "起業",
      "戦略",
      "リーダーシップ",
      "ビジネス",
      "実践",
      "社会科学",
      "経営学",
      "情報",
      "英語",
      "グローバル",
      "対話",
      "教育",
      "論理",
      "サステナビリティ",
      "マーケティング",
      "主体的な学",
      "デザイン",
      "社会学",
      "会計",
      "地域",
      "心理",
      "授業",
      "経済",
      "統計",
      "1年次春学",
      "1年次秋学",
      "さまざまな学",
      "企業分析",
      "卒業論",
      "専門学",
      "心理学",
      "戦略分析",
      "生きた経営学"
    ],
    "needs_review": true,
    "review_note": "公式の学科ページ・研究室紹介ページ・Web体験授業欄から抽出した研究語彙を追加したドラフトです。正式運用前に各学科で確認してください。"
  },
  {
    "id": "biz_marketing",
    "faculty": "経営学部",
    "department": "マーケティング学科",
    "summary": "消費者心理の探索とデータ分析の力で、新たな価値を創造する。",
    "official_url": "https://www.toyo.ac.jp/nyushi/undergraduate/fba/dmrk/",
    "source_basis": "official_department_page",
    "tags": [
      "マーケティング",
      "消費者心理",
      "広告",
      "ブランド",
      "商品企画",
      "データ分析",
      "SNS",
      "心理",
      "データ",
      "ビジネス",
      "経営",
      "経営学",
      "教育",
      "卒業論",
      "1部経営学",
      "マーケティング学",
      "開発",
      "コミュニケーション",
      "マーケティングデータ分析",
      "環境問題",
      "市場",
      "形態",
      "情報",
      "組織"
    ],
    "areas": [
      "ビジネス",
      "心理",
      "データ"
    ],
    "policy_keywords": [
      "マーケティング",
      "消費者心理",
      "広告",
      "ブランド",
      "ビジネス",
      "心理",
      "データ"
    ],
    "research_keywords": [
      "マーケティング",
      "消費者心理",
      "広告",
      "ブランド",
      "商品企画",
      "データ分析",
      "SNS",
      "心理",
      "データ",
      "ビジネス",
      "経営",
      "経営学",
      "教育",
      "卒業論",
      "1部経営学",
      "マーケティング学",
      "開発",
      "コミュニケーション",
      "マーケティングデータ分析",
      "環境問題",
      "市場",
      "形態",
      "情報",
      "組織",
      "統計",
      "マーケティング理論",
      "優秀な卒業論",
      "商品企画・開発",
      "多変量解析",
      "校友会学",
      "活発な討論",
      "経営学部卒業論",
      "重回帰分析"
    ],
    "needs_review": true,
    "review_note": "公式の学科ページ・研究室紹介ページ・Web体験授業欄から抽出した研究語彙を追加したドラフトです。正式運用前に各学科で確認してください。"
  },
  {
    "id": "biz_accounting",
    "faculty": "経営学部",
    "department": "会計ファイナンス学科",
    "summary": "ビジネスの成長を支えるお金の専門性を磨く。",
    "official_url": "https://www.toyo.ac.jp/nyushi/undergraduate/fba/dacf/",
    "source_basis": "official_department_page",
    "tags": [
      "会計",
      "ファイナンス",
      "簿記",
      "金融",
      "投資",
      "企業分析",
      "税務",
      "ビジネス",
      "資格",
      "企業",
      "経営",
      "英語",
      "経済",
      "会計ファイナンス学",
      "コミュニケーション",
      "経営学",
      "グローバル",
      "卒業論",
      "マーケティング",
      "教育",
      "統計",
      "都市",
      "専門的な学",
      "経済学"
    ],
    "areas": [
      "ビジネス",
      "金融",
      "資格"
    ],
    "policy_keywords": [
      "会計",
      "ファイナンス",
      "簿記",
      "金融",
      "ビジネス",
      "金融",
      "資格"
    ],
    "research_keywords": [
      "会計",
      "ファイナンス",
      "簿記",
      "金融",
      "投資",
      "企業分析",
      "税務",
      "ビジネス",
      "資格",
      "企業",
      "経営",
      "英語",
      "経済",
      "会計ファイナンス学",
      "コミュニケーション",
      "経営学",
      "グローバル",
      "卒業論",
      "マーケティング",
      "教育",
      "統計",
      "都市",
      "専門的な学",
      "経済学",
      "インターンシップ",
      "オックスフォード大学",
      "異文化理解",
      "監査法",
      "部経営学",
      "システム",
      "メディア",
      "情報",
      "留学",
      "組織",
      "より専門的な学",
      "アンダーセン監査法"
    ],
    "needs_review": true,
    "review_note": "公式の学科ページ・研究室紹介ページ・Web体験授業欄から抽出した研究語彙を追加したドラフトです。正式運用前に各学科で確認してください。"
  },
  {
    "id": "law_law",
    "faculty": "法学部",
    "department": "法律学科",
    "summary": "論理的思考力と法的視点から問題解決能力を身につける。",
    "official_url": "https://www.toyo.ac.jp/nyushi/undergraduate/law/dlaw/",
    "source_basis": "official_department_page",
    "tags": [
      "法律",
      "裁判",
      "憲法",
      "民法",
      "刑法",
      "行政",
      "公務員",
      "公共",
      "資格",
      "授業",
      "教育",
      "英語",
      "グローバル",
      "政策",
      "法律学",
      "論理",
      "政治・政策",
      "政治学",
      "企業",
      "経済",
      "ロンドン大学",
      "基本六法",
      "無料法",
      "ドイツ・バイロイト大学"
    ],
    "areas": [
      "法律",
      "公共",
      "資格"
    ],
    "policy_keywords": [
      "法律",
      "裁判",
      "憲法",
      "民法",
      "法律",
      "公共",
      "資格"
    ],
    "research_keywords": [
      "法律",
      "裁判",
      "憲法",
      "民法",
      "刑法",
      "行政",
      "公務員",
      "公共",
      "資格",
      "授業",
      "教育",
      "英語",
      "グローバル",
      "政策",
      "法律学",
      "論理",
      "政治・政策",
      "政治学",
      "企業",
      "経済",
      "ロンドン大学",
      "基本六法",
      "無料法",
      "ドイツ・バイロイト大学",
      "憲法・民法・刑法",
      "法律討論",
      "国際社会",
      "国際経済",
      "ICT",
      "価値観",
      "博物館",
      "AI",
      "言語",
      "設計",
      "EU法",
      "いわゆる法"
    ],
    "needs_review": true,
    "review_note": "公式の学科ページ・研究室紹介ページ・Web体験授業欄から抽出した研究語彙を追加したドラフトです。正式運用前に各学科で確認してください。"
  },
  {
    "id": "law_business",
    "faculty": "法学部",
    "department": "企業法学科",
    "summary": "国際的素養と実践的な法的能力を有する企業人を目指す。",
    "official_url": "https://www.toyo.ac.jp/nyushi/undergraduate/law/dbsl/",
    "source_basis": "official_department_page",
    "tags": [
      "企業法",
      "ビジネス法",
      "知的財産",
      "国際取引",
      "コンプライアンス",
      "法律",
      "企業",
      "スポーツ",
      "ビジネス",
      "国際",
      "グローバル",
      "教育",
      "授業",
      "経営",
      "英語",
      "民法",
      "会計",
      "企業法学",
      "経営学",
      "スポーツ法",
      "グローバルビジネス法",
      "ビジネスキャリア法",
      "刑法",
      "哲学"
    ],
    "areas": [
      "法律",
      "ビジネス",
      "国際"
    ],
    "policy_keywords": [
      "企業法",
      "ビジネス法",
      "知的財産",
      "国際取引",
      "法律",
      "ビジネス",
      "国際"
    ],
    "research_keywords": [
      "企業法",
      "ビジネス法",
      "知的財産",
      "国際取引",
      "コンプライアンス",
      "法律",
      "企業",
      "スポーツ",
      "ビジネス",
      "国際",
      "グローバル",
      "教育",
      "授業",
      "経営",
      "英語",
      "民法",
      "会計",
      "企業法学",
      "経営学",
      "スポーツ法",
      "グローバルビジネス法",
      "ビジネスキャリア法",
      "刑法",
      "哲学",
      "憲法",
      "政策",
      "経済",
      "言語",
      "ロンドン大学",
      "会計学",
      "無料法",
      "知的財産法",
      "スポーツ哲学",
      "スポーツ文化論",
      "ドイツ・バイロイト大学",
      "会社法"
    ],
    "needs_review": true,
    "review_note": "公式の学科ページ・研究室紹介ページ・Web体験授業欄から抽出した研究語彙を追加したドラフトです。正式運用前に各学科で確認してください。"
  },
  {
    "id": "soc_sociology",
    "faculty": "社会学部",
    "department": "社会学科",
    "summary": "社会課題に挑む、社会学的想像力をもつ。",
    "official_url": "https://www.toyo.ac.jp/nyushi/undergraduate/soc/dsoc/",
    "source_basis": "official_department_page",
    "tags": [
      "社会学",
      "社会課題",
      "地域",
      "格差",
      "家族",
      "ジェンダー",
      "調査",
      "社会科学",
      "社会調査",
      "教育",
      "英語",
      "グローバル",
      "卒業論",
      "統計",
      "共生",
      "授業",
      "歴史",
      "福祉",
      "社会統計学",
      "エネルギー",
      "バイオマス",
      "地理学",
      "理論社会学",
      "質的調査法"
    ],
    "areas": [
      "社会科学",
      "地域",
      "調査"
    ],
    "policy_keywords": [
      "社会学",
      "社会課題",
      "地域",
      "格差",
      "社会科学",
      "地域",
      "調査"
    ],
    "research_keywords": [
      "社会学",
      "社会課題",
      "地域",
      "格差",
      "家族",
      "ジェンダー",
      "調査",
      "社会科学",
      "社会調査",
      "教育",
      "英語",
      "グローバル",
      "卒業論",
      "統計",
      "共生",
      "授業",
      "歴史",
      "福祉",
      "社会統計学",
      "エネルギー",
      "バイオマス",
      "地理学",
      "理論社会学",
      "質的調査法",
      "高度な調査分析",
      "スポーツ",
      "国際社会",
      "地域振興",
      "食品ロス",
      "多文化",
      "子ども",
      "子育て",
      "倫理",
      "学校",
      "情報",
      "構造"
    ],
    "needs_review": true,
    "review_note": "公式の学科ページ・研究室紹介ページ・Web体験授業欄から抽出した研究語彙を追加したドラフトです。正式運用前に各学科で確認してください。"
  },
  {
    "id": "soc_global",
    "faculty": "社会学部",
    "department": "国際社会学科",
    "summary": "多様性に学び、グローバルな共生社会を創造する。",
    "official_url": "https://www.toyo.ac.jp/nyushi/undergraduate/soc/dgbd/",
    "source_basis": "official_department_page",
    "tags": [
      "国際社会",
      "多文化",
      "移民",
      "共生",
      "グローバル",
      "社会課題",
      "英語",
      "国際",
      "社会科学",
      "社会学",
      "地域",
      "教育",
      "フィールドワーク",
      "社会調査",
      "宗教",
      "留学",
      "ジェンダー",
      "開発",
      "卒業論",
      "国際社会論",
      "インターンシップ",
      "国際社会学",
      "文化人類学",
      "授業"
    ],
    "areas": [
      "国際",
      "社会科学",
      "多文化"
    ],
    "policy_keywords": [
      "国際社会",
      "多文化",
      "移民",
      "共生",
      "国際",
      "社会科学",
      "多文化"
    ],
    "research_keywords": [
      "国際社会",
      "多文化",
      "移民",
      "共生",
      "グローバル",
      "社会課題",
      "英語",
      "国際",
      "社会科学",
      "社会学",
      "地域",
      "教育",
      "フィールドワーク",
      "社会調査",
      "宗教",
      "留学",
      "ジェンダー",
      "開発",
      "卒業論",
      "国際社会論",
      "インターンシップ",
      "国際社会学",
      "文化人類学",
      "授業",
      "コミュニケーション",
      "ネットワーク",
      "宗教社会学",
      "文化社会学",
      "社会学・文化人類学",
      "国際協力",
      "価値観",
      "学校",
      "対話",
      "歴史",
      "組織",
      "経済"
    ],
    "needs_review": true,
    "review_note": "公式の学科ページ・研究室紹介ページ・Web体験授業欄から抽出した研究語彙を追加したドラフトです。正式運用前に各学科で確認してください。"
  },
  {
    "id": "soc_media",
    "faculty": "社会学部",
    "department": "メディアコミュニケーション学科",
    "summary": "多様なメディアの次世代を築くスペシャリストへ。",
    "official_url": "https://www.toyo.ac.jp/nyushi/undergraduate/soc/dmdc/",
    "source_basis": "official_department_page",
    "tags": [
      "メディア",
      "SNS",
      "映像",
      "広告",
      "ジャーナリズム",
      "情報発信",
      "コミュニケーション",
      "社会科学",
      "表現",
      "情報",
      "プログラミング",
      "コンテンツ",
      "出版",
      "メディアコミュニケーション学",
      "授業",
      "教育",
      "ネットワーク",
      "歴史",
      "マスコミ文章作法",
      "卒業論",
      "スポーツ",
      "IoT",
      "アプリ",
      "社会学"
    ],
    "areas": [
      "メディア",
      "表現",
      "社会科学"
    ],
    "policy_keywords": [
      "メディア",
      "SNS",
      "映像",
      "広告",
      "メディア",
      "表現",
      "社会科学"
    ],
    "research_keywords": [
      "メディア",
      "SNS",
      "映像",
      "広告",
      "ジャーナリズム",
      "情報発信",
      "コミュニケーション",
      "社会科学",
      "表現",
      "情報",
      "プログラミング",
      "コンテンツ",
      "出版",
      "メディアコミュニケーション学",
      "授業",
      "教育",
      "ネットワーク",
      "歴史",
      "マスコミ文章作法",
      "卒業論",
      "スポーツ",
      "IoT",
      "アプリ",
      "社会学",
      "AI",
      "企業",
      "経営",
      "編集",
      "論理",
      "都市",
      "さまざまな就活支援",
      "さまざまな就職支援",
      "また学",
      "データベース論",
      "メディア・キャリア論",
      "情報管理論"
    ],
    "needs_review": true,
    "review_note": "公式の学科ページ・研究室紹介ページ・Web体験授業欄から抽出した研究語彙を追加したドラフトです。正式運用前に各学科で確認してください。"
  },
  {
    "id": "soc_psychology",
    "faculty": "社会学部",
    "department": "社会心理学科",
    "summary": "心と社会のつながりを科学する。",
    "official_url": "https://www.toyo.ac.jp/nyushi/undergraduate/soc/dspc/",
    "source_basis": "official_department_page",
    "tags": [
      "心理学",
      "社会心理",
      "人間関係",
      "行動",
      "感情",
      "調査",
      "データ",
      "心理",
      "社会科学",
      "社会心理学",
      "授業",
      "検査",
      "教育",
      "コミュニケーション",
      "データサイエンス",
      "トレーニング",
      "データ分析",
      "卒業論",
      "システム",
      "ICT",
      "SNS",
      "価値観",
      "社会学",
      "AI"
    ],
    "areas": [
      "心理",
      "社会科学",
      "データ"
    ],
    "policy_keywords": [
      "心理学",
      "社会心理",
      "人間関係",
      "行動",
      "心理",
      "社会科学",
      "データ"
    ],
    "research_keywords": [
      "心理学",
      "社会心理",
      "人間関係",
      "行動",
      "感情",
      "調査",
      "データ",
      "心理",
      "社会科学",
      "社会心理学",
      "授業",
      "検査",
      "教育",
      "コミュニケーション",
      "データサイエンス",
      "トレーニング",
      "データ分析",
      "卒業論",
      "システム",
      "ICT",
      "SNS",
      "価値観",
      "社会学",
      "AI",
      "健康",
      "制御",
      "情報",
      "組織",
      "統計",
      "論理",
      "開発",
      "学習自己評価システム",
      "実践的な学",
      "自ら学"
    ],
    "needs_review": true,
    "review_note": "公式の学科ページ・研究室紹介ページ・Web体験授業欄から抽出した研究語彙を追加したドラフトです。正式運用前に各学科で確認してください。"
  },
  {
    "id": "global_ginno",
    "faculty": "国際学部",
    "department": "グローバル・イノベーション学科",
    "summary": "世界を見据えて学び、イノベーションのはじまりに立つ。",
    "official_url": "https://www.toyo.ac.jp/nyushi/undergraduate/grs/dgis/",
    "source_basis": "official_department_page",
    "tags": [
      "国際",
      "イノベーション",
      "英語",
      "起業",
      "課題解決",
      "リーダーシップ",
      "グローバル",
      "ビジネス",
      "実践",
      "留学",
      "経済",
      "インターンシップ",
      "対話",
      "情報",
      "授業",
      "教育",
      "グローバル・イノベーション学",
      "システム",
      "国際社会",
      "企業",
      "哲学",
      "経営",
      "コミュニケーション",
      "ネットワーク"
    ],
    "areas": [
      "国際",
      "ビジネス",
      "実践"
    ],
    "policy_keywords": [
      "国際",
      "イノベーション",
      "英語",
      "起業",
      "国際",
      "ビジネス",
      "実践"
    ],
    "research_keywords": [
      "国際",
      "イノベーション",
      "英語",
      "起業",
      "課題解決",
      "リーダーシップ",
      "グローバル",
      "ビジネス",
      "実践",
      "留学",
      "経済",
      "インターンシップ",
      "対話",
      "情報",
      "授業",
      "教育",
      "グローバル・イノベーション学",
      "システム",
      "国際社会",
      "企業",
      "哲学",
      "経営",
      "コミュニケーション",
      "ネットワーク",
      "日本人学",
      "海外留学",
      "メディア",
      "価値観",
      "社会学",
      "地域",
      "組織",
      "行動",
      "開発",
      "なおグローバル・イノベーション学",
      "人材開発",
      "卒業論"
    ],
    "needs_review": true,
    "review_note": "公式の学科ページ・研究室紹介ページ・Web体験授業欄から抽出した研究語彙を追加したドラフトです。正式運用前に各学科で確認してください。"
  },
  {
    "id": "global_regional",
    "faculty": "国際学部",
    "department": "国際地域学科 国際地域専攻",
    "summary": "グローバルとローカルの視野から発展のための課題解決に貢献する。",
    "official_url": "https://www.toyo.ac.jp/nyushi/undergraduate/grs/rdsc/",
    "source_basis": "official_department_page",
    "tags": [
      "国際地域",
      "開発",
      "地域",
      "国際協力",
      "多文化",
      "観光",
      "政策",
      "国際",
      "社会課題",
      "英語",
      "グローバル",
      "留学",
      "コミュニケーション",
      "教育",
      "イノベーション",
      "交通",
      "情報",
      "都市",
      "インターンシップ",
      "フィールドワーク",
      "国際地域学",
      "異文化理解",
      "インフラ",
      "デザイン"
    ],
    "areas": [
      "国際",
      "地域",
      "社会課題"
    ],
    "policy_keywords": [
      "国際地域",
      "開発",
      "地域",
      "国際協力",
      "国際",
      "地域",
      "社会課題"
    ],
    "research_keywords": [
      "国際地域",
      "開発",
      "地域",
      "国際協力",
      "多文化",
      "観光",
      "政策",
      "国際",
      "社会課題",
      "英語",
      "グローバル",
      "留学",
      "コミュニケーション",
      "教育",
      "イノベーション",
      "交通",
      "情報",
      "都市",
      "インターンシップ",
      "フィールドワーク",
      "国際地域学",
      "異文化理解",
      "インフラ",
      "デザイン",
      "開発支援",
      "社会学",
      "空間",
      "経営",
      "経済",
      "行動",
      "言語",
      "防災",
      "また国際地域学",
      "インターネット・情報",
      "カーティン大学",
      "グローバル・イノベーション学"
    ],
    "needs_review": true,
    "review_note": "公式の学科ページ・研究室紹介ページ・Web体験授業欄から抽出した研究語彙を追加したドラフトです。正式運用前に各学科で確認してください。"
  },
  {
    "id": "tourism",
    "faculty": "国際観光学部",
    "department": "国際観光学科",
    "summary": "世界をつなぐ、観光のプロフェッショナルを目指す。",
    "official_url": "https://www.toyo.ac.jp/nyushi/undergraduate/itm/ditm/",
    "source_basis": "official_department_page",
    "tags": [
      "観光",
      "ホテル",
      "旅行",
      "地域振興",
      "文化",
      "ホスピタリティ",
      "国際",
      "地域",
      "グローバル",
      "観光学",
      "コミュニケーション",
      "まちづくり",
      "政策",
      "教育",
      "フィールドワーク",
      "マーケティング",
      "食文化",
      "企業",
      "市場",
      "英語",
      "行政",
      "インターンシップ",
      "卒業論",
      "国際観光学"
    ],
    "areas": [
      "観光",
      "国際",
      "地域"
    ],
    "policy_keywords": [
      "観光",
      "ホテル",
      "旅行",
      "地域振興",
      "観光",
      "国際",
      "地域"
    ],
    "research_keywords": [
      "観光",
      "ホテル",
      "旅行",
      "地域振興",
      "文化",
      "ホスピタリティ",
      "国際",
      "地域",
      "グローバル",
      "観光学",
      "コミュニケーション",
      "まちづくり",
      "政策",
      "教育",
      "フィールドワーク",
      "マーケティング",
      "食文化",
      "企業",
      "市場",
      "英語",
      "行政",
      "インターンシップ",
      "卒業論",
      "国際観光学",
      "異文化理解",
      "日本文化",
      "価値観",
      "多文化",
      "社会学",
      "交通",
      "会計",
      "共生",
      "宗教",
      "心理",
      "歴史",
      "組織"
    ],
    "needs_review": true,
    "review_note": "公式の学科ページ・研究室紹介ページ・Web体験授業欄から抽出した研究語彙を追加したドラフトです。正式運用前に各学科で確認してください。"
  },
  {
    "id": "ini",
    "faculty": "情報連携学部",
    "department": "情報連携学科",
    "summary": "人と技術を連携し、デジタルの力で未来をつくる。",
    "official_url": "https://www.toyo.ac.jp/nyushi/undergraduate/iniad/diniad/",
    "source_basis": "official_department_page",
    "tags": [
      "情報",
      "プログラミング",
      "AI",
      "デザイン",
      "データ",
      "IoT",
      "UX",
      "教室や",
      "教育",
      "システム",
      "言語",
      "ネットワーク",
      "開発",
      "ICT",
      "コミュニケーション",
      "情報連携学",
      "対話",
      "地域",
      "英語",
      "設計",
      "データサイエンス",
      "人工知能",
      "制御",
      "授業"
    ],
    "areas": [
      "情報",
      "デザイン",
      "データ"
    ],
    "policy_keywords": [
      "情報",
      "プログラミング",
      "AI",
      "デザイン",
      "情報",
      "デザイン",
      "データ"
    ],
    "research_keywords": [
      "情報",
      "プログラミング",
      "AI",
      "デザイン",
      "データ",
      "IoT",
      "UX",
      "教室や",
      "教育",
      "システム",
      "言語",
      "ネットワーク",
      "開発",
      "ICT",
      "コミュニケーション",
      "情報連携学",
      "対話",
      "地域",
      "英語",
      "設計",
      "データサイエンス",
      "人工知能",
      "制御",
      "授業",
      "法律",
      "空間",
      "組織",
      "統計",
      "エネルギー",
      "オンライン教育システム",
      "グローバル",
      "コンテンツ",
      "コンピュータ・システム",
      "研究開発",
      "インフラ",
      "ロボット"
    ],
    "needs_review": true,
    "review_note": "公式の学科ページ・研究室紹介ページ・Web体験授業欄から抽出した研究語彙を追加したドラフトです。正式運用前に各学科で確認してください。"
  },
  {
    "id": "welfare_social",
    "faculty": "福祉社会デザイン学部",
    "department": "社会福祉学科",
    "summary": "多様な人びとの、共生する社会のために学ぶ。",
    "official_url": "https://www.toyo.ac.jp/nyushi/undergraduate/wsd/dswf/",
    "source_basis": "official_department_page",
    "tags": [
      "福祉",
      "社会福祉士",
      "相談支援",
      "共生",
      "高齢者",
      "障害",
      "地域",
      "社会課題",
      "資格",
      "社会福祉",
      "介護",
      "言語",
      "教育",
      "インターンシップ",
      "フィールドワーク",
      "グローバル",
      "学校",
      "栄養",
      "リーダーシップ",
      "ジェンダー",
      "社会福祉学",
      "デザイン",
      "国際社会",
      "子ども"
    ],
    "areas": [
      "福祉",
      "資格",
      "社会課題"
    ],
    "policy_keywords": [
      "福祉",
      "社会福祉士",
      "相談支援",
      "共生",
      "福祉",
      "資格",
      "社会課題"
    ],
    "research_keywords": [
      "福祉",
      "社会福祉士",
      "相談支援",
      "共生",
      "高齢者",
      "障害",
      "地域",
      "社会課題",
      "資格",
      "社会福祉",
      "介護",
      "言語",
      "教育",
      "インターンシップ",
      "フィールドワーク",
      "グローバル",
      "学校",
      "栄養",
      "リーダーシップ",
      "ジェンダー",
      "社会福祉学",
      "デザイン",
      "国際社会",
      "子ども",
      "企業",
      "医療",
      "授業",
      "政策",
      "歴史",
      "経済",
      "英語",
      "行政",
      "刑事司法",
      "卒業論",
      "地域生活支援",
      "実践的学"
    ],
    "needs_review": true,
    "review_note": "公式の学科ページ・研究室紹介ページ・Web体験授業欄から抽出した研究語彙を追加したドラフトです。正式運用前に各学科で確認してください。"
  },
  {
    "id": "welfare_child",
    "faculty": "福祉社会デザイン学部",
    "department": "子ども支援学科",
    "summary": "すべての子どもと家庭、支える人々のために学ぶ。",
    "official_url": "https://www.toyo.ac.jp/nyushi/undergraduate/wsd/dscc/",
    "source_basis": "official_department_page",
    "tags": [
      "子ども",
      "保育",
      "家庭",
      "教育",
      "支援",
      "発達",
      "福祉",
      "子育て",
      "地域",
      "多文化",
      "共生",
      "社会福祉",
      "ICT",
      "情報",
      "コミュニケーション",
      "グローバル",
      "価値観",
      "言語",
      "子育て支援",
      "実践的学",
      "ジェンダー",
      "デザイン",
      "学習支援",
      "日本文化"
    ],
    "areas": [
      "子ども",
      "福祉",
      "教育"
    ],
    "policy_keywords": [
      "子ども",
      "保育",
      "家庭",
      "教育",
      "子ども",
      "福祉",
      "教育"
    ],
    "research_keywords": [
      "子ども",
      "保育",
      "家庭",
      "教育",
      "支援",
      "発達",
      "福祉",
      "子育て",
      "地域",
      "多文化",
      "共生",
      "社会福祉",
      "ICT",
      "情報",
      "コミュニケーション",
      "グローバル",
      "価値観",
      "言語",
      "子育て支援",
      "実践的学",
      "ジェンダー",
      "デザイン",
      "学習支援",
      "日本文化",
      "相談支援",
      "学校",
      "宗教",
      "心理",
      "政策",
      "教職",
      "歴史",
      "空間",
      "英語",
      "開発",
      "また学",
      "また実践的学"
    ],
    "needs_review": true,
    "review_note": "公式の学科ページ・研究室紹介ページ・Web体験授業欄から抽出した研究語彙を追加したドラフトです。正式運用前に各学科で確認してください。"
  },
  {
    "id": "welfare_design",
    "faculty": "福祉社会デザイン学部",
    "department": "人間環境デザイン学科",
    "summary": "人びとに向き合い、寄り添い、支えるデザインへ挑戦する。",
    "official_url": "https://www.toyo.ac.jp/nyushi/undergraduate/wsd/dhed/",
    "source_basis": "official_department_page",
    "tags": [
      "デザイン",
      "住環境",
      "福祉",
      "建築",
      "ユニバーサルデザイン",
      "まちづくり",
      "所属する",
      "空間",
      "情報",
      "プロダクトデザイン",
      "設計",
      "環境デザイン",
      "人間環境",
      "教育",
      "ものづくり",
      "都市",
      "グローバル",
      "地域",
      "生活環境デザイン",
      "空間デザイン",
      "高齢者",
      "言語",
      "人間環境デザイン学",
      "イノベーション"
    ],
    "areas": [
      "デザイン",
      "福祉",
      "建築"
    ],
    "policy_keywords": [
      "デザイン",
      "住環境",
      "福祉",
      "建築",
      "デザイン",
      "福祉",
      "建築"
    ],
    "research_keywords": [
      "デザイン",
      "住環境",
      "福祉",
      "建築",
      "ユニバーサルデザイン",
      "まちづくり",
      "所属する",
      "空間",
      "情報",
      "プロダクトデザイン",
      "設計",
      "環境デザイン",
      "人間環境",
      "教育",
      "ものづくり",
      "都市",
      "グローバル",
      "地域",
      "生活環境デザイン",
      "空間デザイン",
      "高齢者",
      "言語",
      "人間環境デザイン学",
      "イノベーション",
      "人間中心設計",
      "インテリア",
      "人間工学",
      "卒業論",
      "支えるデザイン",
      "システム",
      "メディア",
      "都市計画",
      "IoT",
      "SNS",
      "アプリ",
      "ゲーム"
    ],
    "needs_review": true,
    "review_note": "公式の学科ページ・研究室紹介ページ・Web体験授業欄から抽出した研究語彙を追加したドラフトです。正式運用前に各学科で確認してください。"
  },
  {
    "id": "sports_health",
    "faculty": "健康スポーツ科学部",
    "department": "健康スポーツ科学科",
    "summary": "スポーツを通じて健康を支え、社会に貢献する。",
    "official_url": "https://www.toyo.ac.jp/nyushi/undergraduate/hcs/dspo/",
    "source_basis": "official_department_page",
    "tags": [
      "スポーツ",
      "健康",
      "運動",
      "トレーニング",
      "体育",
      "コーチング",
      "科学",
      "教育",
      "健康スポーツ科学",
      "情報",
      "歴史",
      "グローバル",
      "デザイン",
      "ICT",
      "子ども",
      "高齢者",
      "化学",
      "思想",
      "自然科学",
      "バイオメカニクス",
      "スポーツ情報",
      "コンテンツ",
      "メディア",
      "QOL"
    ],
    "areas": [
      "スポーツ",
      "健康",
      "教育"
    ],
    "policy_keywords": [
      "スポーツ",
      "健康",
      "運動",
      "トレーニング",
      "スポーツ",
      "健康",
      "教育"
    ],
    "research_keywords": [
      "スポーツ",
      "健康",
      "運動",
      "トレーニング",
      "体育",
      "コーチング",
      "科学",
      "教育",
      "健康スポーツ科学",
      "情報",
      "歴史",
      "グローバル",
      "デザイン",
      "ICT",
      "子ども",
      "高齢者",
      "化学",
      "思想",
      "自然科学",
      "バイオメカニクス",
      "スポーツ情報",
      "コンテンツ",
      "メディア",
      "QOL",
      "公務員",
      "生理学",
      "予防",
      "介護",
      "地域",
      "学校",
      "栄養",
      "構造",
      "編集",
      "行政",
      "解剖",
      "都市"
    ],
    "needs_review": true,
    "review_note": "公式の学科ページ・研究室紹介ページ・Web体験授業欄から抽出した研究語彙を追加したドラフトです。正式運用前に各学科で確認してください。"
  },
  {
    "id": "sports_nutrition",
    "faculty": "健康スポーツ科学部",
    "department": "栄養科学科",
    "summary": "健康に生きることを支える栄養を科学する。",
    "official_url": "https://www.toyo.ac.jp/nyushi/undergraduate/hcs/dnss/",
    "source_basis": "official_department_page",
    "tags": [
      "栄養",
      "食",
      "健康",
      "管理栄養士",
      "スポーツ栄養",
      "食品",
      "医療",
      "資格",
      "スポーツ",
      "栄養科学",
      "教育",
      "食環境",
      "トレーニング",
      "QOL",
      "栄養学",
      "グローバル",
      "デザイン",
      "予防",
      "インターンシップ",
      "微生物",
      "生理学",
      "食文化",
      "企業",
      "英語",
      "言語"
    ],
    "areas": [
      "食",
      "健康",
      "資格"
    ],
    "policy_keywords": [
      "栄養",
      "食",
      "健康",
      "管理栄養士",
      "食",
      "健康",
      "資格"
    ],
    "research_keywords": [
      "栄養",
      "食",
      "健康",
      "管理栄養士",
      "スポーツ栄養",
      "食品",
      "医療",
      "資格",
      "スポーツ",
      "栄養科学",
      "教育",
      "食環境",
      "トレーニング",
      "QOL",
      "栄養学",
      "グローバル",
      "デザイン",
      "予防",
      "インターンシップ",
      "微生物",
      "生理学",
      "食文化",
      "企業",
      "英語",
      "言語",
      "運動",
      "スポーツ栄養科学",
      "コミュニケーション",
      "フィールドワーク",
      "エネルギー",
      "ヘルスケア",
      "生活習慣病予防学",
      "食品機能",
      "生物学",
      "免疫",
      "制御",
      "化学"
    ],
    "needs_review": true,
    "review_note": "公式の学科ページ・研究室紹介ページ・Web体験授業欄から抽出した研究語彙を追加したドラフトです。正式運用前に各学科で確認してください。"
  },
  {
    "id": "sci_mechanical",
    "faculty": "理工学部",
    "department": "機械工学科",
    "summary": "暮らしを支えるものづくりの理論と実践を学ぶ。",
    "official_url": "https://www.toyo.ac.jp/nyushi/undergraduate/sce/dmec/",
    "source_basis": "official_department_page",
    "tags": [
      "機械",
      "ロボット",
      "ものづくり",
      "設計",
      "自動車",
      "エネルギー",
      "材料",
      "システム",
      "制御",
      "開発",
      "ロボット工学研究室",
      "制御工学研究室",
      "医用機械工学研究室",
      "熱流体工学研究室",
      "群知能ロボット研究室",
      "設計工学研究室",
      "工学",
      "物理",
      "構造",
      "ゼータ",
      "バイオメカニクス",
      "ヒューマンロボットインタラクション",
      "マイクロ・ナノ構造形成",
      "ロボット工学"
    ],
    "areas": [
      "工学",
      "ものづくり",
      "物理"
    ],
    "policy_keywords": [
      "機械",
      "ロボット",
      "ものづくり",
      "設計",
      "工学",
      "ものづくり",
      "物理"
    ],
    "research_keywords": [
      "機械",
      "ロボット",
      "ものづくり",
      "設計",
      "自動車",
      "エネルギー",
      "材料",
      "システム",
      "制御",
      "開発",
      "ロボット工学研究室",
      "制御工学研究室",
      "医用機械工学研究室",
      "熱流体工学研究室",
      "群知能ロボット研究室",
      "設計工学研究室",
      "工学",
      "物理",
      "構造",
      "ゼータ",
      "バイオメカニクス",
      "ヒューマンロボットインタラクション",
      "マイクロ・ナノ構造形成",
      "ロボット工学",
      "制御工学",
      "医用機械工学",
      "熱流体工学",
      "生体機能デバイス",
      "知能機械システム",
      "群知能ロボット",
      "自動車・交通システム",
      "航空宇宙システム",
      "複雑流体",
      "設計工学",
      "機械工学",
      "シミュレーション"
    ],
    "needs_review": true,
    "review_note": "公式の学科ページ・研究室紹介ページ・Web体験授業欄から抽出した研究語彙を追加したドラフトです。正式運用前に各学科で確認してください。"
  },
  {
    "id": "sci_electrical",
    "faculty": "理工学部",
    "department": "電気電子情報工学科",
    "summary": "指先から地球、宇宙につながる最新技術と創造力を学ぶ。",
    "official_url": "https://www.toyo.ac.jp/nyushi/undergraduate/sce/deec/",
    "source_basis": "official_department_page",
    "tags": [
      "電気",
      "電子",
      "情報",
      "通信",
      "半導体",
      "宇宙",
      "エネルギー",
      "回路",
      "システム",
      "波動情報研究室",
      "物性理論研究室",
      "量子デバイス工学研究室",
      "高電圧・大電流工学研究室",
      "工学",
      "物理",
      "これから本",
      "といったことが好きな人には本",
      "メディアデータサイエンス",
      "ワイヤレス伝送",
      "光エレクトロニクス",
      "同じ",
      "回路システム",
      "機能創発ナノバイオエレクトロニクス",
      "波動情報"
    ],
    "areas": [
      "工学",
      "情報",
      "物理"
    ],
    "policy_keywords": [
      "電気",
      "電子",
      "情報",
      "通信",
      "工学",
      "情報",
      "物理"
    ],
    "research_keywords": [
      "電気",
      "電子",
      "情報",
      "通信",
      "半導体",
      "宇宙",
      "エネルギー",
      "回路",
      "システム",
      "波動情報研究室",
      "物性理論研究室",
      "量子デバイス工学研究室",
      "高電圧・大電流工学研究室",
      "工学",
      "物理",
      "これから本",
      "といったことが好きな人には本",
      "メディアデータサイエンス",
      "ワイヤレス伝送",
      "光エレクトロニクス",
      "同じ",
      "回路システム",
      "機能創発ナノバイオエレクトロニクス",
      "波動情報",
      "物性理論",
      "真空ナノエレクトロニクス",
      "量子デバイス工学",
      "電力システム",
      "電磁エネルギー変換デバイス",
      "高信頼通信ネットワークシステム",
      "高電圧・大電流工学",
      "設計",
      "英語",
      "開発",
      "制御",
      "材料"
    ],
    "needs_review": true,
    "review_note": "公式の学科ページ・研究室紹介ページ・Web体験授業欄から抽出した研究語彙を追加したドラフトです。正式運用前に各学科で確認してください。"
  },
  {
    "id": "sci_chemistry",
    "faculty": "理工学部",
    "department": "応用化学科",
    "summary": "化学を創造力と社会のニーズに応える力にする。",
    "official_url": "https://www.toyo.ac.jp/nyushi/undergraduate/sce/dacm/",
    "source_basis": "official_department_page",
    "tags": [
      "化学",
      "材料",
      "環境",
      "薬品",
      "実験",
      "分子",
      "エネルギー",
      "開発",
      "大気環境科学研究室",
      "有機元素化学研究室",
      "有機合成化学研究室",
      "機能有機化学研究室",
      "理論・計算化学研究室",
      "生命工学研究室",
      "結晶工学研究室",
      "表面化学研究室",
      "超分子化学研究室",
      "食品生物化学研究室",
      "工学",
      "ダイヤモンド",
      "健康的な",
      "分子分光",
      "化学計測",
      "大気環境科学"
    ],
    "areas": [
      "化学",
      "工学",
      "環境"
    ],
    "policy_keywords": [
      "化学",
      "材料",
      "環境",
      "薬品",
      "化学",
      "工学",
      "環境"
    ],
    "research_keywords": [
      "化学",
      "材料",
      "環境",
      "薬品",
      "実験",
      "分子",
      "エネルギー",
      "開発",
      "大気環境科学研究室",
      "有機元素化学研究室",
      "有機合成化学研究室",
      "機能有機化学研究室",
      "理論・計算化学研究室",
      "生命工学研究室",
      "結晶工学研究室",
      "表面化学研究室",
      "超分子化学研究室",
      "食品生物化学研究室",
      "工学",
      "ダイヤモンド",
      "健康的な",
      "分子分光",
      "化学計測",
      "大気環境科学",
      "有機元素化学",
      "有機合成化学",
      "機能有機化学",
      "理論・計算化学",
      "生命工学",
      "結晶工学",
      "表面化学",
      "超分子化学",
      "食品生物化学",
      "構造",
      "電子",
      "教育"
    ],
    "needs_review": true,
    "review_note": "公式の学科ページ・研究室紹介ページ・Web体験授業欄から抽出した研究語彙を追加したドラフトです。正式運用前に各学科で確認してください。"
  },
  {
    "id": "sci_civil",
    "faculty": "理工学部",
    "department": "都市環境デザイン学科",
    "summary": "自然と調和した都市システムを創る。",
    "official_url": "https://www.toyo.ac.jp/nyushi/undergraduate/sce/dcee/",
    "source_basis": "official_department_page",
    "tags": [
      "都市",
      "土木",
      "環境",
      "インフラ",
      "防災",
      "交通",
      "まちづくり",
      "地盤工学研究室",
      "景観工学・ランドスケープデザイン研究室",
      "水工学研究室",
      "空間情報研究室",
      "システム",
      "工学",
      "空間",
      "デザイン",
      "サステイナブル材料・施工",
      "国内・海外旅行することを趣味とする学生は本",
      "地域防災マネジメント",
      "地盤工学",
      "景観工学・ランドスケープデザイン",
      "水工学",
      "社会システムマネジメント",
      "空間情報",
      "防災システム"
    ],
    "areas": [
      "工学",
      "都市",
      "環境"
    ],
    "policy_keywords": [
      "都市",
      "土木",
      "環境",
      "インフラ",
      "工学",
      "都市",
      "環境"
    ],
    "research_keywords": [
      "都市",
      "土木",
      "環境",
      "インフラ",
      "防災",
      "交通",
      "まちづくり",
      "地盤工学研究室",
      "景観工学・ランドスケープデザイン研究室",
      "水工学研究室",
      "空間情報研究室",
      "システム",
      "工学",
      "空間",
      "デザイン",
      "サステイナブル材料・施工",
      "国内・海外旅行することを趣味とする学生は本",
      "地域防災マネジメント",
      "地盤工学",
      "景観工学・ランドスケープデザイン",
      "水工学",
      "社会システムマネジメント",
      "空間情報",
      "防災システム",
      "地域",
      "英語",
      "情報",
      "構造",
      "材料",
      "経営",
      "歴史",
      "行動",
      "設計",
      "都市環境デザイン",
      "シミュレーション",
      "都市システム"
    ],
    "needs_review": true,
    "review_note": "公式の学科ページ・研究室紹介ページ・Web体験授業欄から抽出した研究語彙を追加したドラフトです。正式運用前に各学科で確認してください。"
  },
  {
    "id": "sci_architecture",
    "faculty": "理工学部",
    "department": "建築学科",
    "summary": "快適で安全な建築、まち、生活をデザインする。",
    "official_url": "https://www.toyo.ac.jp/nyushi/undergraduate/sce/darc/",
    "source_basis": "official_department_page",
    "tags": [
      "建築",
      "設計",
      "住宅",
      "都市",
      "デザイン",
      "構造",
      "環境",
      "空間",
      "住環境研究室",
      "地域デザイン研究室",
      "建築デザイン研究室",
      "建築・都市空間デザイン研究室",
      "建築構造・材料研究室",
      "建築環境デザイン研究室",
      "建築設計研究室",
      "木造建築・構造工学研究室",
      "工学",
      "地域",
      "住環境",
      "医療福祉施設",
      "地域デザイン",
      "建築デザイン",
      "建築・都市空間デザイン",
      "建築構造"
    ],
    "areas": [
      "建築",
      "デザイン",
      "工学"
    ],
    "policy_keywords": [
      "建築",
      "設計",
      "住宅",
      "都市",
      "建築",
      "デザイン",
      "工学"
    ],
    "research_keywords": [
      "建築",
      "設計",
      "住宅",
      "都市",
      "デザイン",
      "構造",
      "環境",
      "空間",
      "住環境研究室",
      "地域デザイン研究室",
      "建築デザイン研究室",
      "建築・都市空間デザイン研究室",
      "建築構造・材料研究室",
      "建築環境デザイン研究室",
      "建築設計研究室",
      "木造建築・構造工学研究室",
      "工学",
      "地域",
      "住環境",
      "医療福祉施設",
      "地域デザイン",
      "建築デザイン",
      "建築・都市空間デザイン",
      "建築構造",
      "建築構造・材料",
      "建築環境デザイン",
      "建築生産",
      "建築社会システム",
      "建築設計",
      "木造建築・構造工学",
      "都市計画",
      "高岩",
      "まちづくり",
      "歴史",
      "システム",
      "情報"
    ],
    "needs_review": true,
    "review_note": "公式の学科ページ・研究室紹介ページ・Web体験授業欄から抽出した研究語彙を追加したドラフトです。正式運用前に各学科で確認してください。"
  },
  {
    "id": "info_media",
    "faculty": "総合情報学部",
    "department": "総合情報学科 メディア情報専攻",
    "summary": "文理をつないで、創る、伝える、表現する。",
    "official_url": "https://www.toyo.ac.jp/nyushi/undergraduate/isa/dimi/",
    "source_basis": "official_department_page",
    "tags": [
      "メディア",
      "映像",
      "デザイン",
      "情報",
      "表現",
      "コンテンツ",
      "データ",
      "メディア情報研究室",
      "システム",
      "アプリ",
      "開発",
      "シミュレーション",
      "3年次以降は所属する",
      "スーパーコンピューティング",
      "メディア情報",
      "各領域",
      "年次からは各",
      "文化システム",
      "AI",
      "ゲーム",
      "総合情報学",
      "データサイエンス",
      "プログラミング",
      "対話"
    ],
    "areas": [
      "情報",
      "メディア",
      "表現"
    ],
    "policy_keywords": [
      "メディア",
      "映像",
      "デザイン",
      "情報",
      "情報",
      "メディア",
      "表現"
    ],
    "research_keywords": [
      "メディア",
      "映像",
      "デザイン",
      "情報",
      "表現",
      "コンテンツ",
      "データ",
      "メディア情報研究室",
      "システム",
      "アプリ",
      "開発",
      "シミュレーション",
      "3年次以降は所属する",
      "スーパーコンピューティング",
      "メディア情報",
      "各領域",
      "年次からは各",
      "文化システム",
      "AI",
      "ゲーム",
      "総合情報学",
      "データサイエンス",
      "プログラミング",
      "対話",
      "歴史",
      "留学",
      "ネットワーク",
      "アプリ開発",
      "ロボット",
      "コミュニケーション",
      "制御",
      "英語",
      "言語",
      "価値観",
      "授業",
      "教育"
    ],
    "needs_review": true,
    "review_note": "公式の学科ページ・研究室紹介ページ・Web体験授業欄から抽出した研究語彙を追加したドラフトです。正式運用前に各学科で確認してください。"
  },
  {
    "id": "info_psych_sports",
    "faculty": "総合情報学部",
    "department": "総合情報学科 心理・スポーツ情報専攻",
    "summary": "AIとデータサイエンスで心理学とスポーツ科学を拓く。",
    "official_url": "https://www.toyo.ac.jp/nyushi/undergraduate/isa/dips/",
    "source_basis": "official_department_page",
    "tags": [
      "心理",
      "スポーツ",
      "AI",
      "データサイエンス",
      "分析",
      "健康",
      "情報",
      "数値流体力学研究室",
      "産業・組織心理学研究室",
      "心理学",
      "AI応用と計測",
      "こころとスポーツとIT",
      "先進ソフトウェア",
      "心理とスポーツとIT",
      "数値流体力学",
      "産業・組織心理学",
      "検査",
      "開発",
      "トレーニング",
      "スポーツ情報",
      "統計",
      "スポーツ科学",
      "シミュレーション",
      "行動"
    ],
    "areas": [
      "情報",
      "心理",
      "スポーツ"
    ],
    "policy_keywords": [
      "心理",
      "スポーツ",
      "AI",
      "データサイエンス",
      "情報",
      "心理",
      "スポーツ"
    ],
    "research_keywords": [
      "心理",
      "スポーツ",
      "AI",
      "データサイエンス",
      "分析",
      "健康",
      "情報",
      "数値流体力学研究室",
      "産業・組織心理学研究室",
      "心理学",
      "AI応用と計測",
      "こころとスポーツとIT",
      "先進ソフトウェア",
      "心理とスポーツとIT",
      "数値流体力学",
      "産業・組織心理学",
      "検査",
      "開発",
      "トレーニング",
      "スポーツ情報",
      "統計",
      "スポーツ科学",
      "シミュレーション",
      "行動",
      "運動",
      "コミュニケーション",
      "総合情報学",
      "留学",
      "授業",
      "システム",
      "人工知能",
      "心理情報",
      "社会調査",
      "教育",
      "心理・スポーツ情報",
      "スポーツ心理学"
    ],
    "needs_review": true,
    "review_note": "公式の学科ページ・研究室紹介ページ・Web体験授業欄から抽出した研究語彙を追加したドラフトです。正式運用前に各学科で確認してください。"
  },
  {
    "id": "info_system",
    "faculty": "総合情報学部",
    "department": "総合情報学科 システム情報専攻",
    "summary": "安らぎあふれる社会をデジタルでつくる。",
    "official_url": "https://www.toyo.ac.jp/nyushi/undergraduate/isa/disi/",
    "source_basis": "official_department_page",
    "tags": [
      "システム",
      "プログラミング",
      "AI",
      "データ",
      "ネットワーク",
      "セキュリティ",
      "情報",
      "ソフトウェア科学研究室",
      "知能数理科学研究室",
      "工学",
      "統計",
      "企業",
      "わからないことなどがあれば",
      "ソフトウェア科学",
      "人工知能応用",
      "分散システム",
      "知能数理科学",
      "統計解析",
      "開発",
      "マーケティング",
      "設計",
      "言語",
      "人工知能",
      "教育"
    ],
    "areas": [
      "情報",
      "データ",
      "工学"
    ],
    "policy_keywords": [
      "システム",
      "プログラミング",
      "AI",
      "データ",
      "情報",
      "データ",
      "工学"
    ],
    "research_keywords": [
      "システム",
      "プログラミング",
      "AI",
      "データ",
      "ネットワーク",
      "セキュリティ",
      "情報",
      "ソフトウェア科学研究室",
      "知能数理科学研究室",
      "工学",
      "統計",
      "企業",
      "わからないことなどがあれば",
      "ソフトウェア科学",
      "人工知能応用",
      "分散システム",
      "知能数理科学",
      "統計解析",
      "開発",
      "マーケティング",
      "設計",
      "言語",
      "人工知能",
      "教育",
      "構造",
      "留学",
      "行動",
      "総合情報学",
      "IoT",
      "編集",
      "英語",
      "通信",
      "進化",
      "システム情報",
      "データサイエンス",
      "健康"
    ],
    "needs_review": true,
    "review_note": "公式の学科ページ・研究室紹介ページ・Web体験授業欄から抽出した研究語彙を追加したドラフトです。正式運用前に各学科で確認してください。"
  },
  {
    "id": "env_innovation",
    "faculty": "環境イノベーション学部",
    "department": "環境イノベーション学科",
    "summary": "この地球が、キミのフィールド。環境課題に挑む。",
    "official_url": "https://www.toyo.ac.jp/nyushi/undergraduate/env/",
    "source_basis": "official_department_page",
    "tags": [
      "環境",
      "地球",
      "フィールド",
      "サステナビリティ",
      "気候変動",
      "資源",
      "政策",
      "国際",
      "社会課題",
      "イノベーション",
      "環境イノベーション学",
      "教育",
      "コミュニケーション",
      "生物多様性",
      "地域"
    ],
    "areas": [
      "環境",
      "国際",
      "社会課題"
    ],
    "policy_keywords": [
      "環境",
      "地球",
      "フィールド",
      "サステナビリティ",
      "環境",
      "国際",
      "社会課題"
    ],
    "research_keywords": [
      "環境",
      "地球",
      "フィールド",
      "サステナビリティ",
      "気候変動",
      "資源",
      "政策",
      "国際",
      "社会課題",
      "イノベーション",
      "環境イノベーション学",
      "教育",
      "コミュニケーション",
      "生物多様性",
      "地域"
    ],
    "needs_review": true,
    "review_note": "公式の学科ページ・研究室紹介ページ・Web体験授業欄から抽出した研究語彙を追加したドラフトです。正式運用前に各学科で確認してください。"
  },
  {
    "id": "life_science",
    "faculty": "生命科学部",
    "department": "生命科学科",
    "summary": "いのちのしくみと、いのちを育む環境を科学する。",
    "official_url": "https://www.toyo.ac.jp/nyushi/undergraduate/lsc/dlsc/",
    "source_basis": "official_department_page",
    "tags": [
      "生命科学",
      "動物",
      "細胞",
      "遺伝子",
      "環境",
      "生態",
      "微生物",
      "行動",
      "フィールド動物科学研究室",
      "動物機能形態学研究室",
      "動物細胞工学研究室",
      "放射線微生物学研究室",
      "水環境生態工学研究室",
      "生態リスク学研究室",
      "脳神経科学研究室",
      "行動神経生理学研究室",
      "神経",
      "実験",
      "放射線",
      "フィールド動物科学",
      "動物機能形態学",
      "動物発生システム",
      "動物細胞工学",
      "放射線微生物学"
    ],
    "areas": [
      "生命科学",
      "環境",
      "実験"
    ],
    "policy_keywords": [
      "生命科学",
      "動物",
      "細胞",
      "遺伝子",
      "生命科学",
      "環境",
      "実験"
    ],
    "research_keywords": [
      "生命科学",
      "動物",
      "細胞",
      "遺伝子",
      "環境",
      "生態",
      "微生物",
      "行動",
      "フィールド動物科学研究室",
      "動物機能形態学研究室",
      "動物細胞工学研究室",
      "放射線微生物学研究室",
      "水環境生態工学研究室",
      "生態リスク学研究室",
      "脳神経科学研究室",
      "行動神経生理学研究室",
      "神経",
      "実験",
      "放射線",
      "フィールド動物科学",
      "動物機能形態学",
      "動物発生システム",
      "動物細胞工学",
      "放射線微生物学",
      "水環境生態工学",
      "生態リスク学",
      "生物多様性",
      "神経機能制御",
      "細胞分子毒性",
      "脳神経科学",
      "行動神経生理学",
      "野外調査をベースに研究計画を立てることが多い",
      "化学",
      "情報",
      "健康",
      "生物学"
    ],
    "needs_review": true,
    "review_note": "公式の学科ページ・研究室紹介ページ・Web体験授業欄から抽出した研究語彙を追加したドラフトです。正式運用前に各学科で確認してください。"
  },
  {
    "id": "life_biomedical",
    "faculty": "生命科学部",
    "department": "生体医工学科",
    "summary": "人々の生きるを支える、科学と工学。",
    "official_url": "https://www.toyo.ac.jp/nyushi/undergraduate/lsc/dben/",
    "source_basis": "official_department_page",
    "tags": [
      "医療",
      "工学",
      "健康",
      "リハビリ",
      "医療機器",
      "データ",
      "生命科学",
      "細胞",
      "開発",
      "材料",
      "マイクロ材料工学研究室",
      "免疫システム制御学研究室",
      "医療福祉支援工学研究室",
      "物質医工学研究室",
      "生体情報学研究室",
      "生体高分子材料研究室",
      "細胞ゲノム工学研究室",
      "運動生理学研究室",
      "量子医工学研究室",
      "システム",
      "免疫",
      "治療",
      "ニューロサイエンス",
      "バイオエンジニアリング"
    ],
    "areas": [
      "生命科学",
      "医療",
      "工学"
    ],
    "policy_keywords": [
      "医療",
      "工学",
      "健康",
      "リハビリ",
      "生命科学",
      "医療",
      "工学"
    ],
    "research_keywords": [
      "医療",
      "工学",
      "健康",
      "リハビリ",
      "医療機器",
      "データ",
      "生命科学",
      "細胞",
      "開発",
      "材料",
      "マイクロ材料工学研究室",
      "免疫システム制御学研究室",
      "医療福祉支援工学研究室",
      "物質医工学研究室",
      "生体情報学研究室",
      "生体高分子材料研究室",
      "細胞ゲノム工学研究室",
      "運動生理学研究室",
      "量子医工学研究室",
      "システム",
      "免疫",
      "治療",
      "ニューロサイエンス",
      "バイオエンジニアリング",
      "ヘルスプロモーション",
      "マイクロ材料工学",
      "メディカルロボティクス",
      "免疫システム制御学",
      "医療福祉支援工学",
      "物質医工学",
      "生体信号処理",
      "生体情報学",
      "生体高分子材料",
      "細胞ゲノム工学",
      "運動生理学",
      "量子医工学"
    ],
    "needs_review": true,
    "review_note": "公式の学科ページ・研究室紹介ページ・Web体験授業欄から抽出した研究語彙を追加したドラフトです。正式運用前に各学科で確認してください。"
  },
  {
    "id": "life_bioresource",
    "faculty": "生命科学部",
    "department": "生物資源学科",
    "summary": "生物資源のしくみを学び、持続可能社会をめざす。",
    "official_url": "https://www.toyo.ac.jp/nyushi/undergraduate/lsc/dbre/",
    "source_basis": "official_department_page",
    "tags": [
      "生物資源",
      "植物",
      "微生物",
      "農業",
      "環境",
      "食品",
      "発酵",
      "生命科学",
      "細胞",
      "分子遺伝学研究室",
      "地球環境科学研究室",
      "微生物生理工学研究室",
      "植物バイオーム分子化学研究室",
      "植物生理学研究室",
      "極域微生物機能生態学研究室",
      "極限環境生命科学研究室",
      "極限環境生物資源利用学研究室",
      "環境ストレス応答分子微生物学研究室",
      "生物機能調節化学研究室",
      "糖質材料創成学研究室",
      "遺伝子",
      "酵素",
      "分子遺伝学",
      "地球環境科学"
    ],
    "areas": [
      "生命科学",
      "食",
      "環境"
    ],
    "policy_keywords": [
      "生物資源",
      "植物",
      "微生物",
      "農業",
      "生命科学",
      "食",
      "環境"
    ],
    "research_keywords": [
      "生物資源",
      "植物",
      "微生物",
      "農業",
      "環境",
      "食品",
      "発酵",
      "生命科学",
      "細胞",
      "分子遺伝学研究室",
      "地球環境科学研究室",
      "微生物生理工学研究室",
      "植物バイオーム分子化学研究室",
      "植物生理学研究室",
      "極域微生物機能生態学研究室",
      "極限環境生命科学研究室",
      "極限環境生物資源利用学研究室",
      "環境ストレス応答分子微生物学研究室",
      "生物機能調節化学研究室",
      "糖質材料創成学研究室",
      "遺伝子",
      "酵素",
      "分子遺伝学",
      "地球環境科学",
      "微生物生理工学",
      "応用生体触媒",
      "植物バイオーム分子化学",
      "植物生理学",
      "植物生長制御",
      "極域微生物機能生態学",
      "極限環境生命科学",
      "極限環境生物資源利用学",
      "環境ストレス応答分子微生物学",
      "生物機能調節化学",
      "糖質材料創成学",
      "化学"
    ],
    "needs_review": true,
    "review_note": "公式の学科ページ・研究室紹介ページ・Web体験授業欄から抽出した研究語彙を追加したドラフトです。正式運用前に各学科で確認してください。"
  },
  {
    "id": "food_science",
    "faculty": "食環境科学部",
    "department": "食環境科学科",
    "summary": "次世代の食のあり方を、科学の視点で考える。",
    "official_url": "https://www.toyo.ac.jp/nyushi/undergraduate/fls/dfls/",
    "source_basis": "official_department_page",
    "tags": [
      "食",
      "食品",
      "環境",
      "栄養",
      "安全",
      "科学",
      "フードシステム",
      "食環境",
      "教育",
      "微生物",
      "健康スポーツ科学・保健学研究室",
      "応用生物科学研究室",
      "植物細胞分子生物学研究室",
      "植物育種学研究室",
      "生体高分子化学研究室",
      "糖質生命機能科学研究室",
      "脂質機能科学研究室",
      "調理学研究室",
      "醸造学研究室",
      "食品分析化学研究室",
      "食品微生物学研究室",
      "食品機能論研究室",
      "食物科学研究室",
      "健康",
      "植物"
    ],
    "areas": [
      "食",
      "環境",
      "科学"
    ],
    "policy_keywords": [
      "食",
      "食品",
      "環境",
      "栄養",
      "食",
      "環境",
      "科学"
    ],
    "research_keywords": [
      "食",
      "食品",
      "環境",
      "栄養",
      "安全",
      "科学",
      "フードシステム",
      "食環境",
      "教育",
      "微生物",
      "健康スポーツ科学・保健学研究室",
      "応用生物科学研究室",
      "植物細胞分子生物学研究室",
      "植物育種学研究室",
      "生体高分子化学研究室",
      "糖質生命機能科学研究室",
      "脂質機能科学研究室",
      "調理学研究室",
      "醸造学研究室",
      "食品分析化学研究室",
      "食品微生物学研究室",
      "食品機能論研究室",
      "食物科学研究室",
      "健康",
      "植物",
      "開発",
      "化学",
      "フード・バイオレオロジー",
      "健康スポーツ科学・保健学",
      "当は2024年度からスタートする新しい",
      "応用生物科学",
      "新しい",
      "植物細胞分子生物学",
      "植物育種学",
      "生体高分子化学",
      "科学教育",
      "糖質生命機能科学"
    ],
    "needs_review": true,
    "review_note": "公式の学科ページ・研究室紹介ページ・Web体験授業欄から抽出した研究語彙を追加したドラフトです。正式運用前に各学科で確認してください。"
  },
  {
    "id": "food_data",
    "faculty": "食環境科学部",
    "department": "フードデータサイエンス学科",
    "summary": "データで新たな食の可能性を拓く。",
    "official_url": "https://www.toyo.ac.jp/nyushi/undergraduate/fls/ddsf/",
    "source_basis": "official_department_page",
    "tags": [
      "食",
      "データサイエンス",
      "AI",
      "食品",
      "マーケティング",
      "統計",
      "健康",
      "経済",
      "行動",
      "経済学研究室",
      "行動経済学研究室",
      "食料・資源経済学研究室",
      "食料経済学研究室",
      "データ",
      "ビジネス",
      "サステナブル・マーケティング",
      "フードシステム・食料政策",
      "生体分子制御",
      "経済学",
      "行動経済学",
      "言語習得・言語分析",
      "計算ガストロノミー",
      "食情報・意思決定分析",
      "食料・資源経済学",
      "食料消費行動"
    ],
    "areas": [
      "食",
      "データ",
      "ビジネス"
    ],
    "policy_keywords": [
      "食",
      "データサイエンス",
      "AI",
      "食品",
      "食",
      "データ",
      "ビジネス"
    ],
    "research_keywords": [
      "食",
      "データサイエンス",
      "AI",
      "食品",
      "マーケティング",
      "統計",
      "健康",
      "経済",
      "行動",
      "経済学研究室",
      "行動経済学研究室",
      "食料・資源経済学研究室",
      "食料経済学研究室",
      "データ",
      "ビジネス",
      "サステナブル・マーケティング",
      "フードシステム・食料政策",
      "生体分子制御",
      "経済学",
      "行動経済学",
      "言語習得・言語分析",
      "計算ガストロノミー",
      "食情報・意思決定分析",
      "食料・資源経済学",
      "食料消費行動",
      "食料経済・食料消費",
      "食料経済学",
      "食料経済実験",
      "食行動科学・学習開発",
      "教育",
      "食環境",
      "言語",
      "システム",
      "情報",
      "フードシステム",
      "データ分析",
      "地域"
    ],
    "needs_review": true,
    "review_note": "公式の学科ページ・研究室紹介ページ・Web体験授業欄から抽出した研究語彙を追加したドラフトです。正式運用前に各学科で確認してください。"
  },
  {
    "id": "food_nutrition",
    "faculty": "食環境科学部",
    "department": "健康栄養学科",
    "summary": "人と社会の健康を担う管理栄養士の力を育てる。",
    "official_url": "https://www.toyo.ac.jp/nyushi/undergraduate/fls/dnus/",
    "source_basis": "official_department_page",
    "tags": [
      "栄養",
      "管理栄養士",
      "健康",
      "食事",
      "医療",
      "食品",
      "予防",
      "イギリス・ルネッサンス文化研究室",
      "公衆栄養学研究室",
      "分子食品衛生学研究室",
      "多次元臨床医学研究室",
      "応用栄養学研究室",
      "栄養教育学研究室",
      "栄養生理学研究室",
      "臨床栄養学研究室",
      "臨床栄養管理学研究室",
      "長寿学研究室",
      "食品機能学研究室",
      "食品調理科学研究室",
      "資格",
      "教育",
      "その疑問を解き明かすために当",
      "イギリス・ルネッサンス文化",
      "一見"
    ],
    "areas": [
      "食",
      "健康",
      "資格"
    ],
    "policy_keywords": [
      "栄養",
      "管理栄養士",
      "健康",
      "食事",
      "食",
      "健康",
      "資格"
    ],
    "research_keywords": [
      "栄養",
      "管理栄養士",
      "健康",
      "食事",
      "医療",
      "食品",
      "予防",
      "イギリス・ルネッサンス文化研究室",
      "公衆栄養学研究室",
      "分子食品衛生学研究室",
      "多次元臨床医学研究室",
      "応用栄養学研究室",
      "栄養教育学研究室",
      "栄養生理学研究室",
      "臨床栄養学研究室",
      "臨床栄養管理学研究室",
      "長寿学研究室",
      "食品機能学研究室",
      "食品調理科学研究室",
      "資格",
      "教育",
      "その疑問を解き明かすために当",
      "イギリス・ルネッサンス文化",
      "一見",
      "公衆栄養学",
      "分子食品衛生学",
      "多次元臨床医学",
      "学内",
      "応用栄養学",
      "栄養教育学",
      "栄養生理学",
      "環境衛生",
      "給食経営管理",
      "臨床栄養学",
      "臨床栄養管理学",
      "長寿学"
    ],
    "needs_review": true,
    "review_note": "公式の学科ページ・研究室紹介ページ・Web体験授業欄から抽出した研究語彙を追加したドラフトです。正式運用前に各学科で確認してください。"
  }
]
